{
  "name": "origins.neoorigins.tiny.name",
  "description": "origins.neoorigins.tiny.description",
  "icon": "minecraft:poppy",
  "impact": "medium",
  "order": 16,
  "powers": [
    "neoorigins:tiny/tiny_size",
    "neoorigins:tiny/tiny_wall_climbing",
    "neoorigins:tiny/tiny_speed_boost",
    "neoorigins:tiny/tiny_no_fall_damage",
    "neoorigins:tiny/tiny_attack_penalty",
    "neoorigins:tiny/tiny_hunger_drain"
  ],
  "upgrades": [],
  "tier_powers": [
    {
      "tier": 1,
      "add": [
        "neoorigins:tiny/tiny_evolved_hp"
      ],
      "remove": []
    },
    {
      "tier": 2,
      "add": [
        "neoorigins:tiny/tiny_ascended_hp",
        "neoorigins:tiny/tiny_ascended_speed"
      ],
      "remove": [
        "neoorigins:tiny/tiny_evolved_hp"
      ]
    },
    {
      "tier": 3,
      "add": [
        "neoorigins:tiny/tiny_apex_hp",
        "neoorigins:tiny/tiny_apex_evasion"
      ],
      "remove": [
        "neoorigins:tiny/tiny_ascended_hp"
      ]
    }
  ]
}
